{
  "https://idealista.pt/imovel/34984637": {
    "name": "Apartamento T2 na Rua de Damão, 17, Alhos Vedros, Moita",
    "url": "https://idealista.pt/imovel/34984637",
    "img": "https://img4.idealista.pt/blur/480_360_mq/0/id.pro.pt.image.master/25/e6/88/315508017.jpg",
    "price": "275.000€",
    "in_stock": true,
    "is_blocked": true,
    "last_checked": 1777912506.6039164,
    "phone": null,
    "location": "---",
    "source": "Unknown"
  },
  "https://idealista.pt/imovel/34984631": {
    "name": "Moradia em banda em Baixa da Banheira, Baixa da Banheira e Vale da Amoreira",
    "url": "https://idealista.pt/imovel/34984631",
    "img": "https://img4.idealista.pt/blur/480_360_mq/0/id.pro.pt.image.master/1f/cf/ce/315505305.jpg",
    "price": "215.000€",
    "in_stock": true,
    "is_blocked": true,
    "last_checked": 1777912506.6039164,
    "phone": null,
    "location": "---",
    "source": "Unknown"
  },
  "https://idealista.pt/imovel/34984308": {
    "name": "Apartamento T2 na Rua Bernardino Curado, 36, Centro, Pinhal Novo",
    "url": "https://idealista.pt/imovel/34984308",
    "img": "https://img4.idealista.pt/blur/480_360_mq/0/id.pro.pt.image.master/f6/38/35/315498099.jpg",
    "price": "250.000€",
    "in_stock": true,
    "is_blocked": false,
    "last_checked": 1777912506.6039164,
    "phone": null,
    "location": "---",
    "source": "Unknown"
  },
  "https://idealista.pt/imovel/34960380": {
    "name": "Apartamento T2 em Santo André, Alto do Seixalinho - Santo André - Verderena",
    "url": "https://idealista.pt/imovel/34960380",
    "img": "https://img4.idealista.pt/blur/480_360_mq/0/id.pro.pt.image.master/0f/ce/a3/315491745.jpg",
    "price": "274.900€",
    "in_stock": true,
    "is_blocked": true,
    "last_checked": 1777912506.6039164,
    "phone": null,
    "location": "---",
    "source": "Unknown"
  },
  "https://idealista.pt/imovel/34984131": {
    "name": "Moradia independente em Olhos de Água - Brejos Carreteiros, Quinta do Anjo",
    "url": "https://idealista.pt/imovel/34984131",
    "img": "https://img4.idealista.pt/blur/480_360_mq/0/id.pro.pt.image.master/67/34/fe/315500106.jpg",
    "price": "600.000€",
    "in_stock": true,
    "is_blocked": true,
    "last_checked": 1777912506.6039164,
    "phone": null,
    "location": "---",
    "source": "Unknown"
  },
  "https://idealista.pt/imovel/34983823": {
    "name": "Apartamento T3 na Rua Diogo Cão, s/n, Centro, Pinhal Novo",
    "url": "https://idealista.pt/imovel/34983823",
    "img": "https://img4.idealista.pt/blur/480_360_mq/0/id.pro.pt.image.master/4f/c7/a0/315472398.jpg",
    "price": "348.000€",
    "in_stock": true,
    "is_blocked": true,
    "last_checked": 1777912506.6039164,
    "phone": null,
    "location": "---",
    "source": "Unknown"
  },
  "https://idealista.pt/imovel/34983855": {
    "name": "Apartamento T3 na Rua Diogo Cão, s/n, Centro, Pinhal Novo",
    "url": "https://idealista.pt/imovel/34983855",
    "img": "https://img4.idealista.pt/blur/480_360_mq/0/id.pro.pt.image.master/21/2c/bf/315471962.jpg",
    "price": "318.000€",
    "in_stock": true,
    "is_blocked": true,
    "last_checked": 1777912506.6039164,
    "phone": null,
    "location": "---",
    "source": "Unknown"
  },
  "https://idealista.pt/imovel/34984086": {
    "name": "Apartamento T2 em Lavradio, Barreiro e Lavradio",
    "url": "https://idealista.pt/imovel/34984086",
    "img": "https://img4.idealista.pt/blur/480_360_mq/0/id.pro.pt.image.master/67/d4/6d/315487779.jpg",
    "price": "226.000€",
    "in_stock": true,
    "is_blocked": true,
    "last_checked": 1777912506.6039164,
    "phone": null,
    "location": "---",
    "source": "Unknown"
  },
  "https://idealista.pt/imovel/34983833": {
    "name": "Apartamento T3 em Moita",
    "url": "https://idealista.pt/imovel/34983833",
    "img": "https://img4.idealista.pt/blur/480_360_mq/0/id.pro.pt.image.master/d0/1e/a8/315471757.jpg",
    "price": "315.000€",
    "in_stock": true,
    "is_blocked": true,
    "last_checked": 1777912506.6039164,
    "phone": null,
    "location": "---",
    "source": "Unknown"
  },
  "https://idealista.pt/imovel/34983840": {
    "name": "Apartamento T2 em Baixa da Banheira, Baixa da Banheira e Vale da Amoreira",
    "url": "https://idealista.pt/imovel/34983840",
    "img": "https://img4.idealista.pt/blur/480_360_mq/0/id.pro.pt.image.master/bd/32/9c/315471182.jpg",
    "price": "274.900€",
    "in_stock": true,
    "is_blocked": true,
    "last_checked": 1777912506.6039164,
    "phone": null,
    "location": "---",
    "source": "Unknown"
  },
  "https://idealista.pt/imovel/34983673": {
    "name": "Apartamento T2 na Rua José Augusto Pimenta, s/n, Alto do Seixalinho, Alto do Seixalinho - Santo André - Verderena",
    "url": "https://idealista.pt/imovel/34983673",
    "img": "https://img4.idealista.pt/blur/480_360_mq/0/id.pro.pt.image.master/4a/04/2a/315465453.jpg",
    "price": "205.000€",
    "in_stock": true,
    "is_blocked": true,
    "last_checked": 1777912506.6039164,
    "phone": null,
    "location": "---",
    "source": "Unknown"
  },
  "https://idealista.pt/imovel/34983624": {
    "name": "Apartamento T2 em Baixa da Banheira, Baixa da Banheira e Vale da Amoreira",
    "url": "https://idealista.pt/imovel/34983624",
    "img": "https://img4.idealista.pt/blur/480_360_mq/0/id.pro.pt.image.master/84/62/63/315463212.jpg",
    "price": "220.000€",
    "in_stock": true,
    "is_blocked": true,
    "last_checked": 1777912506.6039164,
    "phone": null,
    "location": "---",
    "source": "Unknown"
  },
  "https://idealista.pt/imovel/34983553": {
    "name": "Apartamento T2 na Praceta Ribeiro Sanches, Alto do Seixalinho, Alto do Seixalinho - Santo André - Verderena",
    "url": "https://idealista.pt/imovel/34983553",
    "img": "https://img4.idealista.pt/blur/480_360_mq/0/id.pro.pt.image.master/84/a4/cf/315462075.jpg",
    "price": "237.500€",
    "in_stock": true,
    "is_blocked": true,
    "last_checked": 1777912506.6039164,
    "phone": null,
    "location": "---",
    "source": "Unknown"
  },
  "https://idealista.pt/imovel/34969161": {
    "name": "Apartamento T3 em Verderena, Alto do Seixalinho - Santo André - Verderena",
    "url": "https://idealista.pt/imovel/34969161",
    "img": "https://img4.idealista.pt/blur/480_360_mq/0/id.pro.pt.image.master/dc/1e/ec/314853496.jpg",
    "price": "269.500€",
    "in_stock": true,
    "is_blocked": true,
    "last_checked": 1777912506.6039164,
    "phone": null,
    "location": "---",
    "source": "Unknown"
  },
  "https://idealista.pt/imovel/34983216": {
    "name": "Apartamento T2 na Rua de Damão, Alhos Vedros, Moita",
    "url": "https://idealista.pt/imovel/34983216",
    "img": "https://img4.idealista.pt/blur/480_360_mq/0/id.pro.pt.image.master/7e/8d/ba/315446277.jpg",
    "price": "275.000€",
    "in_stock": true,
    "is_blocked": true,
    "last_checked": 1777912506.6039164,
    "phone": null,
    "location": "---",
    "source": "Unknown"
  },
  "https://idealista.pt/imovel/34982423": {
    "name": "Apartamento T2 na Rua de Damão, Alhos Vedros, Moita",
    "url": "https://idealista.pt/imovel/34982423",
    "img": "https://img4.idealista.pt/blur/480_360_mq/0/id.pro.pt.image.master/d8/28/16/315418334.jpg",
    "price": "275.000€",
    "in_stock": true,
    "is_blocked": true,
    "last_checked": 1777912506.6039164,
    "phone": null,
    "location": "---",
    "source": "Unknown"
  },
  "https://idealista.pt/imovel/34982388": {
    "name": "Apartamento T2 na Rua de Damão, Alhos Vedros, Moita",
    "url": "https://idealista.pt/imovel/34982388",
    "img": "https://img4.idealista.pt/blur/480_360_mq/0/id.pro.pt.image.master/db/1f/73/315418008.jpg",
    "price": "275.000€",
    "in_stock": true,
    "is_blocked": true,
    "last_checked": 1777912506.6039164,
    "phone": null,
    "location": "---",
    "source": "Unknown"
  },
  "https://idealista.pt/imovel/34971195": {
    "name": "Apartamento T2 em Lavradio, Barreiro e Lavradio",
    "url": "https://idealista.pt/imovel/34971195",
    "img": "https://img4.idealista.pt/blur/480_360_mq/0/id.pro.pt.image.master/07/0e/55/314942483.jpg",
    "price": "226.000€",
    "in_stock": true,
    "is_blocked": true,
    "last_checked": 1777912506.6039164,
    "phone": null,
    "location": "---",
    "source": "Unknown"
  },
  "https://idealista.pt/imovel/34981965": {
    "name": "Apartamento T2 na Rua de Damão, 17, Alhos Vedros, Moita",
    "url": "https://idealista.pt/imovel/34981965",
    "img": "https://img4.idealista.pt/blur/480_360_mq/0/id.pro.pt.image.master/54/51/d4/315396736.jpg",
    "price": "275.000€",
    "in_stock": true,
    "is_blocked": true,
    "last_checked": 1777912506.6039164,
    "phone": null,
    "location": "---",
    "source": "Unknown"
  },
  "https://idealista.pt/imovel/34955663": {
    "name": "Apartamento T2 na Rua José Afonso, s/n, Moita",
    "url": "https://idealista.pt/imovel/34955663",
    "img": "https://img4.idealista.pt/blur/480_360_mq/0/id.pro.pt.image.master/ce/4f/9e/314282470.jpg",
    "price": "230.000€",
    "in_stock": true,
    "is_blocked": true,
    "last_checked": 1777912506.6039164,
    "phone": null,
    "location": "---",
    "source": "Unknown"
  },
  "https://idealista.pt/imovel/34981569": {
    "name": "Moradia independente em Olhos de Água - Brejos Carreteiros, Quinta do Anjo",
    "url": "https://idealista.pt/imovel/34981569",
    "img": "https://img4.idealista.pt/blur/480_360_mq/0/id.pro.pt.image.master/85/ce/14/315374823.jpg",
    "price": "600.000€",
    "in_stock": true,
    "is_blocked": true,
    "last_checked": 1777912506.6039164,
    "phone": null,
    "location": "---",
    "source": "Unknown"
  },
  "https://idealista.pt/imovel/34981512": {
    "name": "Apartamento T3 na Rua Ary dos Santos, 19, Santo António da Charneca, Barreiro",
    "url": "https://idealista.pt/imovel/34981512",
    "img": "https://img4.idealista.pt/blur/480_360_mq/0/id.pro.pt.image.master/ed/76/94/315373673.jpg",
    "price": "335.000€",
    "in_stock": true,
    "is_blocked": false,
    "last_checked": 1777912506.6039164,
    "phone": null,
    "location": "---",
    "source": "Unknown"
  },
  "https://idealista.pt/imovel/34980395": {
    "name": "Moradia independente, moita gaio Rosário e sarilhos pequenos, Gaio-Rosário e Sarilhos Pequenos, Moita",
    "url": "https://idealista.pt/imovel/34980395",
    "img": "https://img4.idealista.pt/blur/480_360_mq/0/id.pro.pt.image.master/23/fe/f1/315365541.jpg",
    "price": "649.900€",
    "in_stock": true,
    "is_blocked": true,
    "last_checked": 1777912506.6039164,
    "phone": null,
    "location": "---",
    "source": "Unknown"
  },
  "https://idealista.pt/imovel/34981451": {
    "name": "Moradia geminada na Rua Henrique Andrade Evans, 9, Santo António da Charneca, Barreiro",
    "url": "https://idealista.pt/imovel/34981451",
    "img": "https://img4.idealista.pt/blur/480_360_mq/0/id.pro.pt.image.master/23/93/06/315373061.jpg",
    "price": "340.000€",
    "in_stock": true,
    "is_blocked": false,
    "last_checked": 1777912506.6039164,
    "phone": null,
    "location": "---",
    "source": "Unknown"
  },
  "https://idealista.pt/imovel/34981455": {
    "name": "Apartamento T2 na Avenida Joaquim José Fernandes, Lavradio, Barreiro e Lavradio",
    "url": "https://idealista.pt/imovel/34981455",
    "img": "https://img4.idealista.pt/blur/480_360_mq/0/id.pro.pt.image.master/87/98/5d/315368040.jpg",
    "price": "260.000€",
    "in_stock": true,
    "is_blocked": true,
    "last_checked": 1777912506.6039164,
    "phone": null,
    "location": "---",
    "source": "Unknown"
  },
  "https://idealista.pt/imovel/34981334": {
    "name": "Apartamento T1 na Rua de Goa, 1, Baixa da Banheira, Baixa da Banheira e Vale da Amoreira",
    "url": "https://idealista.pt/imovel/34981334",
    "img": "https://img4.idealista.pt/blur/480_360_mq/0/id.pro.pt.image.master/66/aa/d7/315364715.jpg",
    "price": "180.000€",
    "in_stock": true,
    "is_blocked": true,
    "last_checked": 1777912506.6039164,
    "phone": null,
    "location": "---",
    "source": "Unknown"
  },
  "https://idealista.pt/imovel/34981236": {
    "name": "Apartamento T2 em Baixa da Banheira, Baixa da Banheira e Vale da Amoreira",
    "url": "https://idealista.pt/imovel/34981236",
    "img": "https://img4.idealista.pt/blur/480_360_mq/0/id.pro.pt.image.master/d9/cc/b6/315363346.jpg",
    "price": "255.000€",
    "in_stock": true,
    "is_blocked": true,
    "last_checked": 1777912506.6039164,
    "phone": null,
    "location": "---",
    "source": "Unknown"
  },
  "https://idealista.pt/imovel/34981212": {
    "name": "Apartamento T2 na Rua de Damão, 17, Alhos Vedros, Moita",
    "url": "https://idealista.pt/imovel/34981212",
    "img": "https://img4.idealista.pt/blur/480_360_mq/0/id.pro.pt.image.master/65/23/96/315359823.jpg",
    "price": "275.000€",
    "in_stock": true,
    "is_blocked": true,
    "last_checked": 1777912506.6039164,
    "phone": null,
    "location": "---",
    "source": "Unknown"
  },
  "https://idealista.pt/imovel/34961269": {
    "name": "Apartamento T1 em Carregueira - Terrim - Lagoa da Palha, Pinhal Novo",
    "url": "https://idealista.pt/imovel/34961269",
    "img": "https://img4.idealista.pt/blur/480_360_mq/0/id.pro.pt.image.master/45/9c/9c/314525336.jpg",
    "price": "329.000€",
    "in_stock": true,
    "is_blocked": true,
    "last_checked": 1777912506.6039164,
    "phone": null,
    "location": "---",
    "source": "Unknown"
  },
  "https://imovirtual.com/pt/anuncio/lavradio-zona-central-apartamento-t3-ID1ihQz": {
    "name": "Lavradio - Zona Central - Apartamento T3",
    "url": "https://imovirtual.com/pt/anuncio/lavradio-zona-central-apartamento-t3-ID1ihQz",
    "img": "https://ireland.apollo.olxcdn.com/v1/files/eyJmbiI6ImtpdzN6Z2c2bnJiaDItQVBUIiwidyI6W3siZm4iOiI2OW5scGE3ZWNxbTcxLUFQVCIsInMiOiIxNCIsInAiOiIxMCwtMTAiLCJhIjoiMCJ9XX0.g8sp27Bor-fM8uFb81ld4ahgpaqZBSfFbijgAl9EKYg/image;s=655x491;q=80",
    "price": "307 000 €",
    "in_stock": true,
    "is_blocked": false,
    "last_checked": 1777912506.6039164,
    "phone": null,
    "location": "---",
    "source": "Unknown"
  },
  "https://imovirtual.com/hpr/pt/anuncio/lavradio-zona-central-apartamento-t3-ID1ihQz": {
    "name": "Lavradio - Zona Central - Apartamento T3",
    "url": "https://imovirtual.com/hpr/pt/anuncio/lavradio-zona-central-apartamento-t3-ID1ihQz",
    "img": null,
    "price": "307 000 €",
    "in_stock": true,
    "is_blocked": false,
    "last_checked": 1777912506.6039164,
    "phone": null,
    "location": "---",
    "source": "Unknown"
  },
  "https://supercasa.pt/venda-apartamento-t2-barreiro/i2196799": {
    "name": "Apartamento T2 em Alto do Seixalinho, Santo André e Verderena, Barreiro",
    "url": "https://supercasa.pt/venda-apartamento-t2-barreiro/i2196799",
    "img": null,
    "price": "274.900 €",
    "in_stock": true,
    "is_blocked": true,
    "last_checked": 1777912506.6039164,
    "phone": null,
    "location": "---",
    "source": "Unknown"
  },
  "https://supercasa.pt/venda-apartamento-t3-barreiro/i2195961": {
    "name": "Apartamento T3 em Alto do Seixalinho, Santo André e Verderena, Barreiro",
    "url": "https://supercasa.pt/venda-apartamento-t3-barreiro/i2195961",
    "img": null,
    "price": "290.000 €",
    "in_stock": true,
    "is_blocked": true,
    "last_checked": 1777912506.6039164,
    "phone": null,
    "location": "---",
    "source": "Unknown"
  },
  "https://supercasa.pt/venda-apartamento-t2-barreiro/i2196849": {
    "name": "Apartamento T2 na Avenida Movimento das Forças Armadas, Alto do Seixalinho, Santo André e Verderena, Barreiro",
    "url": "https://supercasa.pt/venda-apartamento-t2-barreiro/i2196849",
    "img": null,
    "price": "274.000 €",
    "in_stock": true,
    "is_blocked": true,
    "last_checked": 1777912506.6039164,
    "phone": null,
    "location": "---",
    "source": "Unknown"
  },
  "https://supercasa.pt/venda-apartamento-t2-barreiro/i2196970": {
    "name": "Apartamento T2 em Barreiro e Lavradio, Barreiro",
    "url": "https://supercasa.pt/venda-apartamento-t2-barreiro/i2196970",
    "img": null,
    "price": "226.000 €",
    "in_stock": true,
    "is_blocked": true,
    "last_checked": 1777912506.6039164,
    "phone": null,
    "location": "---",
    "source": "Unknown"
  },
  "https://supercasa.pt/venda-apartamento-t2-moita/i2196242": {
    "name": "Apartamento T2 na Moita, Moita",
    "url": "https://supercasa.pt/venda-apartamento-t2-moita/i2196242",
    "img": null,
    "price": "230.000 €",
    "in_stock": true,
    "is_blocked": true,
    "last_checked": 1777912506.6039164,
    "phone": null,
    "location": "---",
    "source": "Unknown"
  },
  "https://supercasa.pt/venda-apartamento-t2-moita/i2196508": {
    "name": "Apartamento T2 em Baixa da Banheira e Vale da Amoreira, Moita",
    "url": "https://supercasa.pt/venda-apartamento-t2-moita/i2196508",
    "img": null,
    "price": "205.000 €",
    "in_stock": true,
    "is_blocked": true,
    "last_checked": 1777912506.6039164,
    "phone": null,
    "location": "---",
    "source": "Unknown"
  },
  "https://supercasa.pt/venda-moradia-t2-moita/i2196535": {
    "name": "Moradia T2 em Baixa da Banheira e Vale da Amoreira, Moita",
    "url": "https://supercasa.pt/venda-moradia-t2-moita/i2196535",
    "img": null,
    "price": "275.000 €",
    "in_stock": true,
    "is_blocked": true,
    "last_checked": 1777912506.6039164,
    "phone": null,
    "location": "---",
    "source": "Unknown"
  },
  "https://supercasa.pt/venda-moradia-t1-moita/i2196952": {
    "name": "Moradia em Banda T1+1 na Rua Jaime Cortesão, Baixa da Banheira e Vale da Amoreira, Moita",
    "url": "https://supercasa.pt/venda-moradia-t1-moita/i2196952",
    "img": null,
    "price": "215.000 €",
    "in_stock": true,
    "is_blocked": true,
    "last_checked": 1777912506.6039164,
    "phone": null,
    "location": "---",
    "source": "Unknown"
  },
  "https://supercasa.pt/venda-apartamento-t3-moita/i2196715": {
    "name": "Apartamento T3 na Moita, Moita",
    "url": "https://supercasa.pt/venda-apartamento-t3-moita/i2196715",
    "img": null,
    "price": "315.000 €",
    "in_stock": true,
    "is_blocked": true,
    "last_checked": 1777912506.6039164,
    "phone": null,
    "location": "---",
    "source": "Unknown"
  }
}